poetry_dev_version/__init__.py
poetry_dev_version/command.py
poetry_dev_version/plugin.py
poetry_dev_version-0.1.5.dist-info/LICENSE
poetry_dev_version-0.1.5.dist-info/METADATA
poetry_dev_version-0.1.5.dist-info/WHEEL
poetry_dev_version-0.1.5.dist-info/entry_points.txt
poetry_dev_version-0.1.5.dist-info/RECORD
