Metadata-Version: 2.1
Name: poetry-dev-version
Version: 0.1.5
Summary: Poetry plugin for development versions
Home-page: https://github.com/alfred82santa/poetry-dev-version
Author: alfred82santa
Author-email: alfred82santa@gmail.com
Requires-Python: >=3.8.1,<4.0
Classifier: Programming Language :: Python :: 3
Classifier: Programming Language :: Python :: 3.9
Classifier: Programming Language :: Python :: 3.10
Classifier: Programming Language :: Python :: 3.11
Requires-Dist: cleo (>=2.0.1)
Requires-Dist: poetry (>=1.4.0)
Project-URL: Repository, https://github.com/alfred82santa/poetry-dev-version
